Metadata-Version: 2.0
Name: odoo9-addon-account-payment-return-import
Version: 9.0.1.0.0
Summary: This module add a generic wizard to import payment return fileformats. Is only the base to be extended by another modules
Home-page: https://www.tecnativa.com
Author: Tecnativa,Odoo Community Association (OCA)
Author-email: support@odoo-community.org
License: AGPL-3
Platform: UNKNOWN
Classifier: Programming Language :: Python :: 2.7
Classifier: Framework :: Odoo
Classifier: License :: OSI Approved :: GNU Affero General Public License v3
Requires-Dist: odoo (<9.1a,>=9.0a)
Requires-Dist: odoo9-addon-account-payment-return
